web_math/__init__.py
web_math/errors.py
web_math/webmath.py
web_math-1.2.0.dist-info/LICENCE
web_math-1.2.0.dist-info/METADATA
web_math-1.2.0.dist-info/WHEEL
web_math-1.2.0.dist-info/top_level.txt
web_math-1.2.0.dist-info/RECORD
