Metadata-Version: 2.1
Name: web-math
Version: 1.2.0
Summary: Online Math Api Wrapper
Home-page: https://github.com/mcbabo/webmath
Author: Moritz Joksch
License: MIT
Keywords: discord discord-calc calculator easy-calc simple-calculator discord.py pycord python math wrapper
Platform: UNKNOWN
Classifier: Development Status :: 5 - Production/Stable
Classifier: Intended Audience :: Education
Classifier: Operating System :: OS Independent
Classifier: License :: OSI Approved :: MIT License
Classifier: Programming Language :: Python :: 3
License-File: LICENCE
Requires-Dist: aiohttp
